hellotestxlc/__init__.py
hellotestxlc/start.py
hellotestxlc-0.1.0.dist-info/LICENSE
hellotestxlc-0.1.0.dist-info/METADATA
hellotestxlc-0.1.0.dist-info/WHEEL
hellotestxlc-0.1.0.dist-info/top_level.txt
hellotestxlc-0.1.0.dist-info/RECORD
