Metadata-Version: 2.1
Name: hellotestxlc
Version: 0.1.0
Summary: A library of tools to quickly expand UI testing
Home-page: https://github.com/cxyboy/hellotestrxlc
Author: xuluocan
Author-email: hijackx@163.com
License: UNKNOWN
Platform: UNKNOWN
Classifier: Programming Language :: Python :: 3
Classifier: License :: OSI Approved :: MIT License
Classifier: Operating System :: OS Independent
Requires-Python: >=3.6
